[{"specName":"SUV","spawnTime":0.5600000000000002},{"specName":"SUV","spawnTime":4.939999999999983},{"specName":"SUV","spawnTime":12.659999999999819},{"specName":"SEDAN","spawnTime":16.119999999999745},{"specName":"COUPE","spawnTime":18.839999999999687},{"specName":"COUPE","spawnTime":20.61999999999965},{"specName":"SUV","spawnTime":23.719999999999583},{"specName":"SEDAN","spawnTime":27.039999999999512},{"specName":"COUPE","spawnTime":32.85999999999954},{"specName":"VAN","spawnTime":34.93999999999986},{"specName":"SUV","spawnTime":37.50000000000026},{"specName":"COUPE","spawnTime":39.52000000000058},{"specName":"SUV","spawnTime":42.94000000000111},{"specName":"VAN","spawnTime":44.620000000001376},{"specName":"VAN","spawnTime":47.02000000000175},{"specName":"VAN","spawnTime":49.44000000000213},{"specName":"COUPE","spawnTime":59.520000000003705},{"specName":"VAN","spawnTime":62.18000000000412},{"specName":"SEDAN","spawnTime":73.80000000000246},{"specName":"SUV","spawnTime":75.90000000000204},{"specName":"COUPE","spawnTime":82.30000000000076},{"specName":"SUV","spawnTime":90.21999999999919},{"specName":"SUV","spawnTime":93.11999999999861},{"specName":"SUV","spawnTime":96.23999999999799},{"specName":"VAN","spawnTime":98.27999999999759},{"specName":"SEDAN","spawnTime":102.2199999999968},{"specName":"COUPE","spawnTime":106.09999999999603},{"specName":"COUPE","spawnTime":113.45999999999457},{"specName":"COUPE","spawnTime":126.65999999999194},{"specName":"SUV","spawnTime":128.659999999992},{"specName":"SUV","spawnTime":134.45999999999498},{"specName":"SUV","spawnTime":138.2399999999969},{"specName":"COUPE","spawnTime":144.4800000000001},{"specName":"VAN","spawnTime":153.24000000000458},{"specName":"VAN","spawnTime":155.74000000000586},{"specName":"VAN","spawnTime":157.88000000000696},{"specName":"COUPE","spawnTime":160.20000000000815},{"specName":"SUV","spawnTime":167.3200000000118},{"specName":"SUV","spawnTime":171.80000000001408},{"specName":"VAN","spawnTime":182.88000000001975},{"specName":"COUPE","spawnTime":187.42000000002207},{"specName":"COUPE","spawnTime":193.160000000025},{"specName":"VAN","spawnTime":195.00000000002595},{"specName":"VAN","spawnTime":198.48000000002773},{"specName":"SEDAN","spawnTime":200.86000000002895},{"specName":"VAN","spawnTime":209.1600000000332},{"specName":"COUPE","spawnTime":212.80000000003506},{"specName":"SUV","spawnTime":216.580000000037},{"specName":"COUPE","spawnTime":219.22000000003834},{"specName":"SEDAN","spawnTime":221.80000000003966},{"specName":"COUPE","spawnTime":225.3800000000415},{"specName":"COUPE","spawnTime":228.38000000004303},{"specName":"SUV","spawnTime":230.00000000004385},{"specName":"VAN","spawnTime":237.16000000004752},{"specName":"VAN","spawnTime":240.2600000000491},{"specName":"VAN","spawnTime":249.88000000005403},{"specName":"VAN","spawnTime":251.90000000005506},{"specName":"SEDAN","spawnTime":254.02000000005614},{"specName":"SEDAN","spawnTime":257.0000000000562},{"specName":"SEDAN","spawnTime":262.24000000005145},{"specName":"SUV","spawnTime":265.20000000004876},{"specName":"VAN","spawnTime":275.90000000003903},{"specName":"SUV","spawnTime":279.08000000003614},{"specName":"SEDAN","spawnTime":280.8600000000345},{"specName":"SUV","spawnTime":283.48000000003213},{"specName":"COUPE","spawnTime":290.1000000000261},{"specName":"SEDAN","spawnTime":292.9600000000235},{"specName":"COUPE","spawnTime":297.78000000001913},{"specName":"VAN","spawnTime":303.1800000000142},{"specName":"VAN","spawnTime":305.1600000000124},{"specName":"COUPE","spawnTime":307.44000000001034},{"specName":"VAN","spawnTime":312.26000000000596},{"specName":"SUV","spawnTime":316.5200000000021},{"specName":"VAN","spawnTime":318.78000000000003},{"specName":"SEDAN","spawnTime":325.0799999999943},{"specName":"SUV","spawnTime":328.2399999999914},{"specName":"SEDAN","spawnTime":332.37999999998766},{"specName":"SUV","spawnTime":336.91999999998353},{"specName":"VAN","spawnTime":342.0399999999789},{"specName":"COUPE","spawnTime":351.8999999999699},{"specName":"SUV","spawnTime":354.13999999996787},{"specName":"COUPE","spawnTime":356.13999999996605},{"specName":"COUPE","spawnTime":359.2999999999632},{"specName":"SEDAN","spawnTime":372.9199999999508},{"specName":"SEDAN","spawnTime":375.8799999999481},{"specName":"SUV","spawnTime":381.2799999999432},{"specName":"COUPE","spawnTime":383.3599999999413},{"specName":"COUPE","spawnTime":405.29999999992134},{"specName":"SUV","spawnTime":407.9799999999189},{"specName":"SEDAN","spawnTime":411.6199999999156},{"specName":"SUV","spawnTime":415.9199999999117},{"specName":"SEDAN","spawnTime":419.8599999999081},{"specName":"VAN","spawnTime":432.8599999998963},{"specName":"COUPE","spawnTime":436.3199999998931},{"specName":"VAN","spawnTime":438.91999999989076},{"specName":"VAN","spawnTime":448.07999999988243},{"specName":"VAN","spawnTime":450.75999999988},{"specName":"COUPE","spawnTime":456.0599999998752},{"specName":"COUPE","spawnTime":463.67999999986824},{"specName":"COUPE","spawnTime":465.7999999998663},{"specName":"SEDAN","spawnTime":481.2199999998523},{"specName":"SEDAN","spawnTime":483.47999999985024},{"specName":"SEDAN","spawnTime":486.95999999984707},{"specName":"SUV","spawnTime":491.2399999998432},{"specName":"COUPE","spawnTime":505.43999999983026},{"specName":"VAN","spawnTime":508.1199999998278},{"specName":"SEDAN","spawnTime":521.4799999998157},{"specName":"SUV","spawnTime":528.4199999998094},{"specName":"SEDAN","spawnTime":532.4399999998058},{"specName":"SEDAN","spawnTime":534.7999999998036},{"specName":"VAN","spawnTime":536.519999999802},{"specName":"COUPE","spawnTime":540.3599999997986},{"specName":"VAN","spawnTime":545.9999999997934},{"specName":"SUV","spawnTime":550.839999999789},{"specName":"SEDAN","spawnTime":555.7999999997845},{"specName":"COUPE","spawnTime":577.5399999997647},{"specName":"SUV","spawnTime":590.1599999997533},{"specName":"VAN","spawnTime":595.5199999997484},{"specName":"SEDAN","spawnTime":597.7599999997464},{"specName":"SUV","spawnTime":605.0999999997397},{"specName":"SUV","spawnTime":606.919999999738},{"specName":"SUV","spawnTime":609.9199999997353},{"specName":"SUV","spawnTime":619.7399999997264},{"specName":"SEDAN","spawnTime":625.3999999997212},{"specName":"COUPE","spawnTime":636.659999999711},{"specName":"VAN","spawnTime":646.3399999997022},{"specName":"COUPE","spawnTime":653.1999999996959},{"specName":"VAN","spawnTime":655.0399999996943},{"specName":"SUV","spawnTime":659.77999999969},{"specName":"SEDAN","spawnTime":670.4399999996803},{"specName":"SEDAN","spawnTime":677.1399999996742},{"specName":"SEDAN","spawnTime":682.2999999996695},{"specName":"VAN","spawnTime":684.8399999996672},{"specName":"VAN","spawnTime":692.3399999996603},{"specName":"SUV","spawnTime":707.7399999996463},{"specName":"SEDAN","spawnTime":713.539999999641},{"specName":"COUPE","spawnTime":718.019999999637},{"specName":"SEDAN","spawnTime":720.6799999996346},{"specName":"VAN","spawnTime":727.4199999996284},{"specName":"SUV","spawnTime":729.9999999996261},{"specName":"VAN","spawnTime":731.7399999996245},{"specName":"SUV","spawnTime":736.4399999996202},{"specName":"VAN","spawnTime":749.0999999996087},{"specName":"COUPE","spawnTime":756.9199999996016},{"specName":"SEDAN","spawnTime":760.0199999995988},{"specName":"COUPE","spawnTime":770.3999999995893},{"specName":"COUPE","spawnTime":780.8399999995798},{"specName":"COUPE","spawnTime":783.6399999995773},{"specName":"VAN","spawnTime":790.1199999995714},{"specName":"SEDAN","spawnTime":796.2399999995658},{"specName":"VAN","spawnTime":819.8399999995444},{"specName":"VAN","spawnTime":823.2999999995412},{"specName":"VAN","spawnTime":826.819999999538},{"specName":"VAN","spawnTime":828.7399999995363},{"specName":"SEDAN","spawnTime":834.2199999995313},{"specName":"COUPE","spawnTime":837.5599999995283},{"specName":"SUV","spawnTime":840.7399999995254},{"specName":"SUV","spawnTime":845.3999999995211},{"specName":"SUV","spawnTime":848.3799999995184},{"specName":"VAN","spawnTime":856.7799999995108},{"specName":"VAN","spawnTime":860.879999999507},{"specName":"SEDAN","spawnTime":862.8399999995053},{"specName":"SEDAN","spawnTime":864.6199999995036},{"specName":"COUPE","spawnTime":866.6199999995018},{"specName":"VAN","spawnTime":870.2799999994985},{"specName":"SEDAN","spawnTime":874.6799999994945},{"specName":"COUPE","spawnTime":878.1199999994914},{"specName":"COUPE","spawnTime":884.2599999994858},{"specName":"COUPE","spawnTime":888.8399999994816},{"specName":"VAN","spawnTime":898.5599999994728},{"specName":"SUV","spawnTime":901.8799999994698},{"specName":"SUV","spawnTime":904.5599999994673},{"specName":"COUPE","spawnTime":908.6399999994636},{"specName":"COUPE","spawnTime":911.9999999994606},{"specName":"SUV","spawnTime":914.3199999994584},{"specName":"VAN","spawnTime":916.8799999994561},{"specName":"VAN","spawnTime":922.9999999994506},{"specName":"SEDAN","spawnTime":931.9399999994424},{"specName":"COUPE","spawnTime":935.0599999994396},{"specName":"VAN","spawnTime":936.839999999438},{"specName":"COUPE","spawnTime":940.0199999994351},{"specName":"COUPE","spawnTime":942.6199999994327},{"specName":"SUV","spawnTime":947.7199999994281},{"specName":"VAN","spawnTime":956.6999999994199},{"specName":"VAN","spawnTime":959.0799999994177},{"specName":"VAN","spawnTime":961.3599999994157},{"specName":"SUV","spawnTime":970.5999999994073},{"specName":"SUV","spawnTime":974.1199999994041},{"specName":"SEDAN","spawnTime":980.9799999993978},{"specName":"COUPE","spawnTime":991.0999999993886},{"specName":"VAN","spawnTime":998.8399999993816}]
