[{"specName":"COUPE","spawnTime":3.000000000000002},{"specName":"SUV","spawnTime":6.759999999999944},{"specName":"VAN","spawnTime":9.459999999999887},{"specName":"COUPE","spawnTime":12.079999999999831},{"specName":"VAN","spawnTime":14.01999999999979},{"specName":"SEDAN","spawnTime":17.21999999999972},{"specName":"SEDAN","spawnTime":19.399999999999675},{"specName":"SEDAN","spawnTime":23.45999999999959},{"specName":"COUPE","spawnTime":25.27999999999955},{"specName":"SEDAN","spawnTime":27.939999999999493},{"specName":"SUV","spawnTime":31.499999999999417},{"specName":"SUV","spawnTime":34.97999999999987},{"specName":"COUPE","spawnTime":36.66000000000013},{"specName":"SUV","spawnTime":39.70000000000061},{"specName":"SEDAN","spawnTime":42.560000000001054},{"specName":"VAN","spawnTime":44.38000000000134},{"specName":"SUV","spawnTime":47.9800000000019},{"specName":"SEDAN","spawnTime":51.260000000002414},{"specName":"COUPE","spawnTime":56.40000000000322},{"specName":"SUV","spawnTime":60.860000000003915},{"specName":"VAN","spawnTime":64.46000000000431},{"specName":"SUV","spawnTime":67.26000000000376},{"specName":"COUPE","spawnTime":70.38000000000314},{"specName":"SEDAN","spawnTime":72.00000000000281},{"specName":"COUPE","spawnTime":75.42000000000213},{"specName":"SUV","spawnTime":79.02000000000142},{"specName":"SEDAN","spawnTime":82.30000000000076},{"specName":"COUPE","spawnTime":85.40000000000015},{"specName":"VAN","spawnTime":87.95999999999964},{"specName":"SEDAN","spawnTime":92.89999999999866},{"specName":"SUV","spawnTime":95.61999999999811},{"specName":"COUPE","spawnTime":104.37999999999637},{"specName":"SEDAN","spawnTime":107.19999999999581},{"specName":"COUPE","spawnTime":108.97999999999546},{"specName":"SEDAN","spawnTime":112.43999999999477},{"specName":"SUV","spawnTime":114.45999999999437},{"specName":"SUV","spawnTime":117.23999999999381},{"specName":"VAN","spawnTime":120.8599999999931},{"specName":"VAN","spawnTime":123.65999999999254},{"specName":"COUPE","spawnTime":127.59999999999175},{"specName":"COUPE","spawnTime":130.15999999999278},{"specName":"SEDAN","spawnTime":133.03999999999425},{"specName":"SEDAN","spawnTime":135.61999999999557},{"specName":"SEDAN","spawnTime":137.51999999999654},{"specName":"SUV","spawnTime":139.53999999999758},{"specName":"SUV","spawnTime":143.4799999999996},{"specName":"SEDAN","spawnTime":145.22000000000048},{"specName":"COUPE","spawnTime":147.74000000000177},{"specName":"SEDAN","spawnTime":150.3400000000031},{"specName":"VAN","spawnTime":154.30000000000513},{"specName":"SEDAN","spawnTime":159.86000000000797},{"specName":"VAN","spawnTime":169.42000000001286},{"specName":"COUPE","spawnTime":174.52000000001547},{"specName":"VAN","spawnTime":176.38000000001642},{"specName":"COUPE","spawnTime":180.00000000001828},{"specName":"SUV","spawnTime":182.8000000000197},{"specName":"SEDAN","spawnTime":184.5600000000206},{"specName":"SEDAN","spawnTime":186.42000000002156},{"specName":"VAN","spawnTime":189.92000000002335},{"specName":"VAN","spawnTime":193.5400000000252},{"specName":"SUV","spawnTime":195.24000000002607},{"specName":"SUV","spawnTime":198.08000000002752},{"specName":"SEDAN","spawnTime":200.2000000000286},{"specName":"VAN","spawnTime":204.860000000031},{"specName":"SUV","spawnTime":206.68000000003192},{"specName":"VAN","spawnTime":210.9600000000341},{"specName":"VAN","spawnTime":213.38000000003535},{"specName":"VAN","spawnTime":217.5600000000375},{"specName":"SUV","spawnTime":219.86000000003867},{"specName":"VAN","spawnTime":222.24000000003988},{"specName":"VAN","spawnTime":224.48000000004103},{"specName":"VAN","spawnTime":228.58000000004313},{"specName":"COUPE","spawnTime":230.38000000004405},{"specName":"COUPE","spawnTime":235.28000000004656},{"specName":"SEDAN","spawnTime":237.82000000004786},{"specName":"SUV","spawnTime":248.54000000005334},{"specName":"COUPE","spawnTime":254.36000000005632},{"specName":"SUV","spawnTime":256.9000000000563},{"specName":"COUPE","spawnTime":259.80000000005367},{"specName":"VAN","spawnTime":261.4400000000522},{"specName":"SEDAN","spawnTime":263.88000000004996},{"specName":"SEDAN","spawnTime":266.10000000004794},{"specName":"VAN","spawnTime":268.9800000000453},{"specName":"SUV","spawnTime":279.5800000000357},{"specName":"SEDAN","spawnTime":284.2600000000314},{"specName":"SEDAN","spawnTime":287.4600000000285},{"specName":"SEDAN","spawnTime":289.8800000000263},{"specName":"COUPE","spawnTime":292.3400000000241},{"specName":"VAN","spawnTime":299.7600000000173},{"specName":"COUPE","spawnTime":301.6600000000156},{"specName":"SUV","spawnTime":304.36000000001314},{"specName":"VAN","spawnTime":306.700000000011},{"specName":"COUPE","spawnTime":308.5600000000093},{"specName":"COUPE","spawnTime":310.6800000000074},{"specName":"VAN","spawnTime":312.48000000000576},{"specName":"COUPE","spawnTime":316.5000000000021},{"specName":"SUV","spawnTime":318.78000000000003},{"specName":"SEDAN","spawnTime":320.7999999999982},{"specName":"SEDAN","spawnTime":326.21999999999326},{"specName":"VAN","spawnTime":329.3399999999904},{"specName":"SUV","spawnTime":334.49999999998573},{"specName":"SUV","spawnTime":336.9399999999835},{"specName":"COUPE","spawnTime":340.17999999998057},{"specName":"COUPE","spawnTime":342.7799999999782},{"specName":"VAN","spawnTime":344.6799999999765},{"specName":"SEDAN","spawnTime":347.1999999999742},{"specName":"VAN","spawnTime":350.0199999999716},{"specName":"VAN","spawnTime":352.07999999996974},{"specName":"SEDAN","spawnTime":356.45999999996576},{"specName":"SUV","spawnTime":358.9199999999635},{"specName":"SEDAN","spawnTime":361.43999999996123},{"specName":"SUV","spawnTime":365.9599999999571},{"specName":"SUV","spawnTime":372.2199999999514},{"specName":"SUV","spawnTime":374.2199999999496},{"specName":"SEDAN","spawnTime":379.8199999999445},{"specName":"VAN","spawnTime":381.85999999994266},{"specName":"SUV","spawnTime":387.2999999999377},{"specName":"VAN","spawnTime":390.4199999999349},{"specName":"SEDAN","spawnTime":396.4399999999294},{"specName":"SEDAN","spawnTime":400.55999999992565},{"specName":"SEDAN","spawnTime":403.07999999992336},{"specName":"SUV","spawnTime":405.1199999999215},{"specName":"COUPE","spawnTime":407.13999999991967},{"specName":"COUPE","spawnTime":415.539999999912},{"specName":"VAN","spawnTime":417.35999999991037},{"specName":"SUV","spawnTime":425.0199999999034},{"specName":"COUPE","spawnTime":426.93999999990166},{"specName":"SUV","spawnTime":432.6399999998965},{"specName":"COUPE","spawnTime":436.3599999998931},{"specName":"SEDAN","spawnTime":440.6399999998892},{"specName":"SUV","spawnTime":443.23999999988683},{"specName":"SEDAN","spawnTime":447.3399999998831},{"specName":"VAN","spawnTime":452.23999999987865},{"specName":"SEDAN","spawnTime":455.09999999987605},{"specName":"VAN","spawnTime":457.39999999987396},{"specName":"COUPE","spawnTime":460.4399999998712},{"specName":"COUPE","spawnTime":463.33999999986855},{"specName":"SUV","spawnTime":466.4999999998657},{"specName":"SUV","spawnTime":468.5599999998638},{"specName":"VAN","spawnTime":471.4399999998612},{"specName":"SEDAN","spawnTime":474.23999999985864},{"specName":"SUV","spawnTime":476.07999999985697},{"specName":"COUPE","spawnTime":478.83999999985446},{"specName":"SEDAN","spawnTime":480.5199999998529},{"specName":"SUV","spawnTime":483.5199999998502},{"specName":"SUV","spawnTime":486.11999999984783},{"specName":"SEDAN","spawnTime":491.2199999998432},{"specName":"SEDAN","spawnTime":493.33999999984127},{"specName":"SUV","spawnTime":496.23999999983863},{"specName":"SUV","spawnTime":503.37999999983214},{"specName":"COUPE","spawnTime":512.7399999998237},{"specName":"VAN","spawnTime":515.3999999998213},{"specName":"COUPE","spawnTime":518.5399999998184},{"specName":"VAN","spawnTime":520.9999999998162},{"specName":"COUPE","spawnTime":526.0399999998116},{"specName":"VAN","spawnTime":528.819999999809},{"specName":"SEDAN","spawnTime":533.0999999998052},{"specName":"SEDAN","spawnTime":538.4199999998003},{"specName":"COUPE","spawnTime":540.6799999997983},{"specName":"SEDAN","spawnTime":554.0199999997861},{"specName":"SUV","spawnTime":561.2799999997795},{"specName":"SUV","spawnTime":567.1799999997742},{"specName":"VAN","spawnTime":572.6999999997691},{"specName":"VAN","spawnTime":575.119999999767},{"specName":"SUV","spawnTime":581.699999999761},{"specName":"SEDAN","spawnTime":586.4399999997567},{"specName":"COUPE","spawnTime":589.1199999997542},{"specName":"COUPE","spawnTime":594.4399999997494},{"specName":"VAN","spawnTime":601.6999999997428},{"specName":"SUV","spawnTime":604.6199999997401},{"specName":"VAN","spawnTime":606.3599999997385},{"specName":"COUPE","spawnTime":608.3399999997367},{"specName":"COUPE","spawnTime":611.2599999997341},{"specName":"COUPE","spawnTime":614.9199999997307},{"specName":"VAN","spawnTime":617.7199999997282},{"specName":"SUV","spawnTime":621.199999999725},{"specName":"COUPE","spawnTime":623.1599999997233},{"specName":"COUPE","spawnTime":624.9199999997217},{"specName":"SEDAN","spawnTime":627.0799999997197},{"specName":"COUPE","spawnTime":631.7999999997154},{"specName":"SUV","spawnTime":639.4999999997084},{"specName":"SEDAN","spawnTime":641.7799999997063},{"specName":"VAN","spawnTime":646.3999999997021},{"specName":"COUPE","spawnTime":648.1599999997005},{"specName":"VAN","spawnTime":650.979999999698},{"specName":"COUPE","spawnTime":652.6799999996964},{"specName":"COUPE","spawnTime":657.8199999996917},{"specName":"COUPE","spawnTime":662.959999999687},{"specName":"SUV","spawnTime":666.4599999996839},{"specName":"VAN","spawnTime":668.3599999996821},{"specName":"VAN","spawnTime":673.5599999996774},{"specName":"COUPE","spawnTime":677.4999999996738},{"specName":"COUPE","spawnTime":684.7799999996672},{"specName":"COUPE","spawnTime":689.0599999996633},{"specName":"VAN","spawnTime":692.7799999996599},{"specName":"COUPE","spawnTime":695.6399999996573},{"specName":"VAN","spawnTime":697.5399999996556},{"specName":"COUPE","spawnTime":699.6799999996537},{"specName":"COUPE","spawnTime":703.1199999996505},{"specName":"SUV","spawnTime":708.3399999996458},{"specName":"SUV","spawnTime":710.6399999996437},{"specName":"SUV","spawnTime":712.5999999996419},{"specName":"SUV","spawnTime":716.5999999996383},{"specName":"COUPE","spawnTime":718.8999999996362},{"specName":"VAN","spawnTime":727.859999999628},{"specName":"SEDAN","spawnTime":730.6199999996255},{"specName":"VAN","spawnTime":735.8399999996208},{"specName":"VAN","spawnTime":744.339999999613},{"specName":"SUV","spawnTime":746.8399999996108},{"specName":"COUPE","spawnTime":748.8999999996089},{"specName":"VAN","spawnTime":751.2199999996068},{"specName":"COUPE","spawnTime":757.8399999996008},{"specName":"SUV","spawnTime":761.8799999995971},{"specName":"SEDAN","spawnTime":766.9199999995925},{"specName":"COUPE","spawnTime":768.6599999995909},{"specName":"SUV","spawnTime":779.8999999995807},{"specName":"VAN","spawnTime":784.019999999577},{"specName":"COUPE","spawnTime":789.2999999995722},{"specName":"COUPE","spawnTime":794.999999999567},{"specName":"COUPE","spawnTime":796.9599999995652},{"specName":"SUV","spawnTime":803.2799999995594},{"specName":"VAN","spawnTime":807.8399999995553},{"specName":"VAN","spawnTime":822.439999999542},{"specName":"COUPE","spawnTime":825.6199999995391},{"specName":"SUV","spawnTime":829.9399999995352},{"specName":"VAN","spawnTime":832.2799999995331},{"specName":"COUPE","spawnTime":834.0799999995314},{"specName":"SEDAN","spawnTime":839.5599999995264},{"specName":"SUV","spawnTime":845.3199999995212},{"specName":"VAN","spawnTime":851.7199999995154},{"specName":"VAN","spawnTime":855.5399999995119},{"specName":"SUV","spawnTime":863.0599999995051},{"specName":"SUV","spawnTime":869.0399999994996},{"specName":"COUPE","spawnTime":871.2399999994976},{"specName":"SUV","spawnTime":873.9999999994951},{"specName":"VAN","spawnTime":877.3199999994921},{"specName":"VAN","spawnTime":879.0599999994905},{"specName":"COUPE","spawnTime":882.0399999994878},{"specName":"COUPE","spawnTime":886.0199999994842},{"specName":"COUPE","spawnTime":888.2599999994821},{"specName":"COUPE","spawnTime":894.7999999994762},{"specName":"SUV","spawnTime":901.0599999994705},{"specName":"SEDAN","spawnTime":903.3199999994685},{"specName":"SUV","spawnTime":908.159999999464},{"specName":"SEDAN","spawnTime":910.5399999994619},{"specName":"VAN","spawnTime":913.4199999994593},{"specName":"SUV","spawnTime":915.959999999457},{"specName":"COUPE","spawnTime":919.4199999994538},{"specName":"VAN","spawnTime":921.8399999994516},{"specName":"SEDAN","spawnTime":923.63999999945},{"specName":"SUV","spawnTime":927.5599999994464},{"specName":"SUV","spawnTime":933.0599999994414},{"specName":"COUPE","spawnTime":939.3799999994357},{"specName":"VAN","spawnTime":944.479999999431},{"specName":"SEDAN","spawnTime":948.4199999994274},{"specName":"COUPE","spawnTime":950.3599999994257},{"specName":"VAN","spawnTime":953.8199999994225},{"specName":"SUV","spawnTime":959.859999999417},{"specName":"VAN","spawnTime":962.6999999994144},{"specName":"COUPE","spawnTime":966.6999999994108},{"specName":"VAN","spawnTime":969.819999999408},{"specName":"COUPE","spawnTime":975.5199999994028},{"specName":"COUPE","spawnTime":978.5199999994},{"specName":"COUPE","spawnTime":981.5599999993973},{"specName":"SUV","spawnTime":989.7399999993899},{"specName":"SUV","spawnTime":992.0599999993877},{"specName":"COUPE","spawnTime":994.1999999993858},{"specName":"SUV","spawnTime":996.6999999993835},{"specName":"VAN","spawnTime":998.8599999993816}]
