[{"specName":"VAN","spawnTime":6.499999999999949},{"specName":"VAN","spawnTime":9.539999999999885},{"specName":"SUV","spawnTime":13.279999999999806},{"specName":"SUV","spawnTime":15.079999999999767},{"specName":"SEDAN","spawnTime":19.13999999999968},{"specName":"COUPE","spawnTime":27.21999999999951},{"specName":"COUPE","spawnTime":33.099999999999575},{"specName":"SUV","spawnTime":35.019999999999875},{"specName":"COUPE","spawnTime":45.94000000000158},{"specName":"SEDAN","spawnTime":51.720000000002486},{"specName":"VAN","spawnTime":54.460000000002914},{"specName":"SUV","spawnTime":68.24000000000356},{"specName":"SEDAN","spawnTime":72.82000000000265},{"specName":"VAN","spawnTime":88.97999999999944},{"specName":"VAN","spawnTime":94.33999999999837},{"specName":"VAN","spawnTime":108.61999999999553},{"specName":"SUV","spawnTime":112.21999999999481},{"specName":"SEDAN","spawnTime":118.05999999999365},{"specName":"VAN","spawnTime":119.85999999999329},{"specName":"SUV","spawnTime":123.37999999999259},{"specName":"SUV","spawnTime":135.39999999999546},{"specName":"COUPE","spawnTime":137.97999999999678},{"specName":"SEDAN","spawnTime":139.9999999999978},{"specName":"VAN","spawnTime":142.83999999999926},{"specName":"SUV","spawnTime":148.62000000000222},{"specName":"SEDAN","spawnTime":151.78000000000384},{"specName":"SEDAN","spawnTime":154.68000000000532},{"specName":"SUV","spawnTime":163.2200000000097},{"specName":"COUPE","spawnTime":167.90000000001208},{"specName":"SUV","spawnTime":172.18000000001427},{"specName":"SUV","spawnTime":181.96000000001928},{"specName":"VAN","spawnTime":183.82000000002023},{"specName":"SUV","spawnTime":187.20000000002196},{"specName":"VAN","spawnTime":193.58000000002522},{"specName":"SUV","spawnTime":196.2600000000266},{"specName":"SUV","spawnTime":201.52000000002928},{"specName":"COUPE","spawnTime":206.96000000003207},{"specName":"SEDAN","spawnTime":210.04000000003364},{"specName":"SUV","spawnTime":213.20000000003526},{"specName":"VAN","spawnTime":239.6600000000488},{"specName":"COUPE","spawnTime":244.82000000005144},{"specName":"SEDAN","spawnTime":246.86000000005248},{"specName":"VAN","spawnTime":249.10000000005363},{"specName":"VAN","spawnTime":254.06000000005616},{"specName":"SEDAN","spawnTime":273.66000000004107},{"specName":"COUPE","spawnTime":278.4400000000367},{"specName":"COUPE","spawnTime":288.5800000000275},{"specName":"SEDAN","spawnTime":291.84000000002453},{"specName":"VAN","spawnTime":293.7200000000228},{"specName":"VAN","spawnTime":295.6200000000211},{"specName":"SEDAN","spawnTime":305.66000000001196},{"specName":"SEDAN","spawnTime":317.00000000000165},{"specName":"SUV","spawnTime":336.89999999998355},{"specName":"COUPE","spawnTime":348.2999999999732},{"specName":"VAN","spawnTime":371.73999999995186},{"specName":"COUPE","spawnTime":393.7799999999318},{"specName":"VAN","spawnTime":400.09999999992607},{"specName":"VAN","spawnTime":407.6399999999192},{"specName":"COUPE","spawnTime":409.8799999999172},{"specName":"VAN","spawnTime":419.59999999990833},{"specName":"VAN","spawnTime":421.4199999999067},{"specName":"SEDAN","spawnTime":427.81999999990086},{"specName":"SEDAN","spawnTime":446.1399999998842},{"specName":"SEDAN","spawnTime":448.7799999998818},{"specName":"VAN","spawnTime":450.4399999998803},{"specName":"SEDAN","spawnTime":457.19999999987414},{"specName":"VAN","spawnTime":467.9199999998644},{"specName":"COUPE","spawnTime":473.89999999985895},{"specName":"SUV","spawnTime":480.27999999985315},{"specName":"COUPE","spawnTime":486.87999999984714},{"specName":"SEDAN","spawnTime":492.35999999984216},{"specName":"SUV","spawnTime":504.23999999983135},{"specName":"SEDAN","spawnTime":506.7399999998291},{"specName":"SUV","spawnTime":509.9199999998262},{"specName":"COUPE","spawnTime":513.3399999998231},{"specName":"COUPE","spawnTime":524.439999999813},{"specName":"COUPE","spawnTime":534.319999999804},{"specName":"VAN","spawnTime":536.0799999998025},{"specName":"COUPE","spawnTime":539.879999999799},{"specName":"SEDAN","spawnTime":546.3399999997931},{"specName":"SUV","spawnTime":550.0799999997897},{"specName":"VAN","spawnTime":556.9999999997834},{"specName":"COUPE","spawnTime":567.4599999997739},{"specName":"COUPE","spawnTime":572.5199999997693},{"specName":"COUPE","spawnTime":580.7399999997618},{"specName":"COUPE","spawnTime":604.5999999997401},{"specName":"VAN","spawnTime":607.1999999997378},{"specName":"COUPE","spawnTime":617.899999999728},{"specName":"VAN","spawnTime":621.4199999997248},{"specName":"VAN","spawnTime":628.6799999997182},{"specName":"COUPE","spawnTime":631.3399999997158},{"specName":"VAN","spawnTime":634.439999999713},{"specName":"VAN","spawnTime":640.1799999997078},{"specName":"COUPE","spawnTime":644.6599999997037},{"specName":"SUV","spawnTime":647.7599999997009},{"specName":"SUV","spawnTime":649.9799999996989},{"specName":"SEDAN","spawnTime":652.6599999996964},{"specName":"COUPE","spawnTime":663.8199999996863},{"specName":"VAN","spawnTime":672.6399999996783},{"specName":"VAN","spawnTime":674.4799999996766},{"specName":"SUV","spawnTime":703.5799999996501},{"specName":"COUPE","spawnTime":706.2799999996477},{"specName":"SUV","spawnTime":718.6799999996364},{"specName":"SUV","spawnTime":721.4799999996338},{"specName":"COUPE","spawnTime":725.3799999996303},{"specName":"SEDAN","spawnTime":738.0399999996188},{"specName":"SEDAN","spawnTime":740.9999999996161},{"specName":"SEDAN","spawnTime":766.5599999995928},{"specName":"COUPE","spawnTime":768.3199999995912},{"specName":"COUPE","spawnTime":772.7999999995872},{"specName":"SEDAN","spawnTime":775.6599999995846},{"specName":"COUPE","spawnTime":785.1799999995759},{"specName":"COUPE","spawnTime":790.6599999995709},{"specName":"SUV","spawnTime":802.8799999995598},{"specName":"SUV","spawnTime":816.3599999995475},{"specName":"SEDAN","spawnTime":843.5199999995228},{"specName":"SUV","spawnTime":845.2199999995213},{"specName":"VAN","spawnTime":848.6999999995181},{"specName":"SUV","spawnTime":850.6199999995164},{"specName":"SUV","spawnTime":873.3999999994957},{"specName":"SEDAN","spawnTime":882.6799999994872},{"specName":"SUV","spawnTime":885.3399999994848},{"specName":"VAN","spawnTime":891.3799999994793},{"specName":"SUV","spawnTime":893.979999999477},{"specName":"COUPE","spawnTime":907.4599999994647},{"specName":"COUPE","spawnTime":912.3599999994602},{"specName":"SUV","spawnTime":915.7799999994571},{"specName":"SUV","spawnTime":920.1999999994531},{"specName":"VAN","spawnTime":924.2799999994494},{"specName":"SUV","spawnTime":930.6399999994436},{"specName":"COUPE","spawnTime":949.3399999994266},{"specName":"VAN","spawnTime":955.3799999994211},{"specName":"COUPE","spawnTime":957.3199999994193},{"specName":"SUV","spawnTime":970.7599999994071},{"specName":"SUV","spawnTime":987.319999999392}]
