[{"specName":"COUPE","spawnTime":0.9600000000000005},{"specName":"VAN","spawnTime":5.599999999999969},{"specName":"VAN","spawnTime":10.73999999999986},{"specName":"SUV","spawnTime":14.719999999999775},{"specName":"SEDAN","spawnTime":18.559999999999693},{"specName":"SEDAN","spawnTime":24.999999999999556},{"specName":"SUV","spawnTime":30.259999999999444},{"specName":"SUV","spawnTime":42.440000000001035},{"specName":"SUV","spawnTime":46.36000000000165},{"specName":"SEDAN","spawnTime":51.42000000000244},{"specName":"COUPE","spawnTime":54.90000000000298},{"specName":"SEDAN","spawnTime":61.820000000004065},{"specName":"SEDAN","spawnTime":67.42000000000372},{"specName":"SEDAN","spawnTime":73.76000000000246},{"specName":"VAN","spawnTime":84.88000000000025},{"specName":"COUPE","spawnTime":98.45999999999755},{"specName":"SEDAN","spawnTime":102.35999999999677},{"specName":"COUPE","spawnTime":114.07999999999444},{"specName":"VAN","spawnTime":117.87999999999369},{"specName":"COUPE","spawnTime":127.07999999999186},{"specName":"VAN","spawnTime":136.49999999999602},{"specName":"SEDAN","spawnTime":142.41999999999905},{"specName":"SUV","spawnTime":147.2200000000015},{"specName":"COUPE","spawnTime":160.02000000000805},{"specName":"SUV","spawnTime":163.4200000000098},{"specName":"VAN","spawnTime":171.38000000001387},{"specName":"SUV","spawnTime":175.22000000001583},{"specName":"VAN","spawnTime":185.40000000002104},{"specName":"COUPE","spawnTime":189.66000000002322},{"specName":"COUPE","spawnTime":194.26000000002557},{"specName":"COUPE","spawnTime":197.54000000002725},{"specName":"SEDAN","spawnTime":206.68000000003192},{"specName":"SUV","spawnTime":214.20000000003577},{"specName":"SEDAN","spawnTime":217.88000000003765},{"specName":"SEDAN","spawnTime":232.18000000004497},{"specName":"COUPE","spawnTime":240.74000000004935},{"specName":"VAN","spawnTime":246.04000000005206},{"specName":"COUPE","spawnTime":250.56000000005437},{"specName":"COUPE","spawnTime":255.34000000005682},{"specName":"VAN","spawnTime":277.42000000003765},{"specName":"COUPE","spawnTime":301.84000000001544},{"specName":"SUV","spawnTime":307.0400000000107},{"specName":"COUPE","spawnTime":312.84000000000543},{"specName":"COUPE","spawnTime":323.69999999999555},{"specName":"SUV","spawnTime":329.6999999999901},{"specName":"SUV","spawnTime":337.89999999998264},{"specName":"COUPE","spawnTime":344.57999999997656},{"specName":"VAN","spawnTime":349.3999999999722},{"specName":"VAN","spawnTime":361.39999999996127},{"specName":"SUV","spawnTime":373.4399999999503},{"specName":"SEDAN","spawnTime":378.9799999999453},{"specName":"SEDAN","spawnTime":388.9799999999362},{"specName":"VAN","spawnTime":395.75999999993},{"specName":"COUPE","spawnTime":399.5999999999265},{"specName":"COUPE","spawnTime":404.4599999999221},{"specName":"VAN","spawnTime":408.8399999999181},{"specName":"VAN","spawnTime":417.61999999991014},{"specName":"VAN","spawnTime":422.6999999999055},{"specName":"SUV","spawnTime":427.3399999999013},{"specName":"SUV","spawnTime":433.41999999989577},{"specName":"COUPE","spawnTime":441.1799999998887},{"specName":"SUV","spawnTime":444.4599999998857},{"specName":"SUV","spawnTime":451.4999999998793},{"specName":"SEDAN","spawnTime":459.3399999998722},{"specName":"SEDAN","spawnTime":463.2599999998686},{"specName":"SEDAN","spawnTime":469.8999999998626},{"specName":"SUV","spawnTime":475.67999999985733},{"specName":"SEDAN","spawnTime":481.8999999998517},{"specName":"SUV","spawnTime":485.7199999998482},{"specName":"VAN","spawnTime":492.9599999998416},{"specName":"VAN","spawnTime":500.19999999983503},{"specName":"VAN","spawnTime":509.2199999998268},{"specName":"SUV","spawnTime":512.8199999998236},{"specName":"COUPE","spawnTime":519.2599999998178},{"specName":"SUV","spawnTime":532.9999999998053},{"specName":"SUV","spawnTime":540.3199999997986},{"specName":"SUV","spawnTime":545.0199999997943},{"specName":"VAN","spawnTime":550.859999999789},{"specName":"SEDAN","spawnTime":554.3399999997858},{"specName":"SEDAN","spawnTime":561.7799999997791},{"specName":"VAN","spawnTime":570.4399999997712},{"specName":"SEDAN","spawnTime":580.9799999997616},{"specName":"VAN","spawnTime":584.3599999997585},{"specName":"SEDAN","spawnTime":591.519999999752},{"specName":"VAN","spawnTime":595.5799999997483},{"specName":"SEDAN","spawnTime":599.3599999997449},{"specName":"SEDAN","spawnTime":604.3599999997404},{"specName":"SEDAN","spawnTime":607.7599999997373},{"specName":"SEDAN","spawnTime":613.1399999997324},{"specName":"SEDAN","spawnTime":617.4199999997285},{"specName":"VAN","spawnTime":622.4999999997239},{"specName":"SUV","spawnTime":631.9199999997153},{"specName":"VAN","spawnTime":635.8399999997117},{"specName":"VAN","spawnTime":639.9999999997079},{"specName":"VAN","spawnTime":645.5999999997028},{"specName":"VAN","spawnTime":649.4599999996993},{"specName":"SUV","spawnTime":665.4199999996848},{"specName":"VAN","spawnTime":674.1799999996769},{"specName":"COUPE","spawnTime":683.2599999996686},{"specName":"VAN","spawnTime":691.7799999996608},{"specName":"COUPE","spawnTime":696.2599999996568},{"specName":"COUPE","spawnTime":701.1999999996523},{"specName":"COUPE","spawnTime":716.7999999996381},{"specName":"SUV","spawnTime":720.3999999996348},{"specName":"SEDAN","spawnTime":728.2599999996277},{"specName":"SUV","spawnTime":731.6599999996246},{"specName":"VAN","spawnTime":736.3199999996203},{"specName":"SUV","spawnTime":743.0599999996142},{"specName":"SEDAN","spawnTime":749.4999999996083},{"specName":"SUV","spawnTime":756.7399999996018},{"specName":"VAN","spawnTime":769.5599999995901},{"specName":"SUV","spawnTime":774.9399999995852},{"specName":"SUV","spawnTime":782.919999999578},{"specName":"COUPE","spawnTime":796.2399999995658},{"specName":"SEDAN","spawnTime":800.0799999995623},{"specName":"VAN","spawnTime":803.5999999995591},{"specName":"SEDAN","spawnTime":808.2799999995549},{"specName":"SEDAN","spawnTime":813.8999999995498},{"specName":"VAN","spawnTime":818.3799999995457},{"specName":"SUV","spawnTime":821.9199999995425},{"specName":"COUPE","spawnTime":832.359999999533},{"specName":"SEDAN","spawnTime":838.6199999995273},{"specName":"COUPE","spawnTime":846.3399999995203},{"specName":"VAN","spawnTime":850.2199999995167},{"specName":"SUV","spawnTime":854.9399999995125},{"specName":"VAN","spawnTime":864.4999999995038},{"specName":"SUV","spawnTime":870.4799999994983},{"specName":"SUV","spawnTime":880.6199999994891},{"specName":"COUPE","spawnTime":886.6999999994836},{"specName":"COUPE","spawnTime":891.779999999479},{"specName":"SUV","spawnTime":897.7399999994735},{"specName":"SEDAN","spawnTime":901.7599999994699},{"specName":"COUPE","spawnTime":911.3599999994611},{"specName":"COUPE","spawnTime":914.8799999994579},{"specName":"SEDAN","spawnTime":921.419999999452},{"specName":"SEDAN","spawnTime":941.0399999994341},{"specName":"SUV","spawnTime":950.5199999994255},{"specName":"SEDAN","spawnTime":954.7399999994217},{"specName":"SEDAN","spawnTime":958.6999999994181},{"specName":"COUPE","spawnTime":968.659999999409},{"specName":"SEDAN","spawnTime":972.8599999994052},{"specName":"COUPE","spawnTime":980.6799999993981},{"specName":"COUPE","spawnTime":984.5199999993946},{"specName":"SEDAN","spawnTime":991.9199999993879},{"specName":"SUV","spawnTime":997.6799999993826}]
