[{"specName":"VAN","spawnTime":6.619999999999947},{"specName":"COUPE","spawnTime":8.599999999999905},{"specName":"COUPE","spawnTime":10.319999999999869},{"specName":"SUV","spawnTime":19.499999999999673},{"specName":"VAN","spawnTime":23.719999999999583},{"specName":"SUV","spawnTime":26.71999999999952},{"specName":"COUPE","spawnTime":30.85999999999943},{"specName":"SEDAN","spawnTime":32.5999999999995},{"specName":"SEDAN","spawnTime":34.439999999999785},{"specName":"COUPE","spawnTime":36.20000000000006},{"specName":"VAN","spawnTime":37.86000000000032},{"specName":"SEDAN","spawnTime":41.360000000000866},{"specName":"SUV","spawnTime":46.0400000000016},{"specName":"SUV","spawnTime":49.84000000000219},{"specName":"COUPE","spawnTime":55.240000000003036},{"specName":"COUPE","spawnTime":59.5000000000037},{"specName":"SEDAN","spawnTime":61.36000000000399},{"specName":"VAN","spawnTime":63.420000000004315},{"specName":"VAN","spawnTime":82.94000000000064},{"specName":"SUV","spawnTime":86.69999999999989},{"specName":"SEDAN","spawnTime":88.41999999999955},{"specName":"SUV","spawnTime":92.1999999999988},{"specName":"VAN","spawnTime":105.69999999999611},{"specName":"COUPE","spawnTime":108.63999999999552},{"specName":"SEDAN","spawnTime":119.07999999999345},{"specName":"COUPE","spawnTime":125.61999999999215},{"specName":"SUV","spawnTime":127.27999999999182},{"specName":"VAN","spawnTime":132.85999999999416},{"specName":"VAN","spawnTime":135.39999999999546},{"specName":"VAN","spawnTime":139.43999999999753},{"specName":"SEDAN","spawnTime":141.95999999999881},{"specName":"VAN","spawnTime":144.6600000000002},{"specName":"VAN","spawnTime":148.88000000000235},{"specName":"SEDAN","spawnTime":151.9200000000039},{"specName":"SEDAN","spawnTime":162.14000000000914},{"specName":"SEDAN","spawnTime":163.90000000001004},{"specName":"SUV","spawnTime":166.5400000000114},{"specName":"SUV","spawnTime":169.00000000001265},{"specName":"VAN","spawnTime":173.0000000000147},{"specName":"SEDAN","spawnTime":178.8600000000177},{"specName":"SEDAN","spawnTime":180.76000000001866},{"specName":"SEDAN","spawnTime":182.46000000001953},{"specName":"SUV","spawnTime":187.00000000002186},{"specName":"SUV","spawnTime":189.260000000023},{"specName":"COUPE","spawnTime":193.48000000002517},{"specName":"VAN","spawnTime":196.8600000000269},{"specName":"SUV","spawnTime":199.04000000002802},{"specName":"COUPE","spawnTime":202.44000000002976},{"specName":"SUV","spawnTime":205.74000000003144},{"specName":"SUV","spawnTime":210.00000000003362},{"specName":"COUPE","spawnTime":212.34000000003482},{"specName":"SEDAN","spawnTime":214.0400000000357},{"specName":"COUPE","spawnTime":216.72000000003706},{"specName":"VAN","spawnTime":220.58000000003904},{"specName":"COUPE","spawnTime":223.58000000004057},{"specName":"SEDAN","spawnTime":226.26000000004194},{"specName":"SUV","spawnTime":234.28000000004604},{"specName":"SEDAN","spawnTime":237.80000000004785},{"specName":"SUV","spawnTime":242.96000000005048},{"specName":"COUPE","spawnTime":247.16000000005263},{"specName":"VAN","spawnTime":251.62000000005492},{"specName":"SUV","spawnTime":255.4800000000569},{"specName":"SEDAN","spawnTime":260.70000000005285},{"specName":"VAN","spawnTime":262.48000000005123},{"specName":"SEDAN","spawnTime":266.96000000004716},{"specName":"SUV","spawnTime":273.14000000004154},{"specName":"SEDAN","spawnTime":303.1800000000142},{"specName":"COUPE","spawnTime":312.0000000000062},{"specName":"COUPE","spawnTime":317.0800000000016},{"specName":"COUPE","spawnTime":324.91999999999445},{"specName":"SUV","spawnTime":330.51999999998935},{"specName":"SEDAN","spawnTime":332.49999999998755},{"specName":"SUV","spawnTime":337.57999999998293},{"specName":"SEDAN","spawnTime":350.09999999997154},{"specName":"COUPE","spawnTime":354.5399999999675},{"specName":"SUV","spawnTime":359.11999999996334},{"specName":"SUV","spawnTime":379.8199999999445},{"specName":"COUPE","spawnTime":386.49999999993844},{"specName":"SEDAN","spawnTime":393.8799999999317},{"specName":"SEDAN","spawnTime":400.0799999999261},{"specName":"COUPE","spawnTime":403.0199999999234},{"specName":"COUPE","spawnTime":405.5399999999211},{"specName":"SUV","spawnTime":410.3799999999167},{"specName":"SUV","spawnTime":414.7999999999127},{"specName":"SUV","spawnTime":421.3999999999067},{"specName":"SEDAN","spawnTime":424.2599999999041},{"specName":"VAN","spawnTime":426.8799999999017},{"specName":"SUV","spawnTime":428.7799999999},{"specName":"COUPE","spawnTime":434.11999999989513},{"specName":"COUPE","spawnTime":436.5599999998929},{"specName":"SUV","spawnTime":439.57999999989016},{"specName":"SEDAN","spawnTime":443.9599999998862},{"specName":"SEDAN","spawnTime":445.8199999998845},{"specName":"SEDAN","spawnTime":448.4399999998821},{"specName":"SUV","spawnTime":452.0799999998788},{"specName":"SEDAN","spawnTime":458.9199999998726},{"specName":"SEDAN","spawnTime":464.31999999986766},{"specName":"SEDAN","spawnTime":477.9399999998553},{"specName":"COUPE","spawnTime":487.2599999998468},{"specName":"COUPE","spawnTime":490.8999999998435},{"specName":"VAN","spawnTime":497.75999999983725},{"specName":"VAN","spawnTime":510.59999999982557},{"specName":"SEDAN","spawnTime":513.9199999998226},{"specName":"SEDAN","spawnTime":515.9399999998208},{"specName":"VAN","spawnTime":519.2599999998178},{"specName":"SUV","spawnTime":521.6799999998155},{"specName":"VAN","spawnTime":528.1199999998097},{"specName":"VAN","spawnTime":533.4799999998048},{"specName":"SUV","spawnTime":535.6199999998029},{"specName":"SUV","spawnTime":549.2599999997905},{"specName":"COUPE","spawnTime":557.2199999997832},{"specName":"COUPE","spawnTime":558.9399999997817},{"specName":"COUPE","spawnTime":561.6999999997792},{"specName":"COUPE","spawnTime":564.3399999997768},{"specName":"COUPE","spawnTime":566.7799999997745},{"specName":"COUPE","spawnTime":579.3199999997631},{"specName":"SEDAN","spawnTime":582.3599999997604},{"specName":"SEDAN","spawnTime":587.3199999997559},{"specName":"VAN","spawnTime":598.9799999997452},{"specName":"COUPE","spawnTime":600.7599999997436},{"specName":"SUV","spawnTime":611.8199999997336},{"specName":"SUV","spawnTime":614.9599999997307},{"specName":"VAN","spawnTime":619.5399999997265},{"specName":"SEDAN","spawnTime":632.5599999997147},{"specName":"COUPE","spawnTime":650.6399999996983},{"specName":"SEDAN","spawnTime":653.8199999996954},{"specName":"COUPE","spawnTime":657.3599999996921},{"specName":"COUPE","spawnTime":661.2799999996886},{"specName":"SUV","spawnTime":670.8799999996799},{"specName":"SEDAN","spawnTime":676.239999999675},{"specName":"VAN","spawnTime":678.8599999996726},{"specName":"SUV","spawnTime":683.2599999996686},{"specName":"COUPE","spawnTime":701.499999999652},{"specName":"VAN","spawnTime":706.8599999996471},{"specName":"SEDAN","spawnTime":711.6599999996428},{"specName":"SEDAN","spawnTime":723.539999999632},{"specName":"COUPE","spawnTime":727.5999999996283},{"specName":"SUV","spawnTime":729.9599999996261},{"specName":"COUPE","spawnTime":732.4399999996239},{"specName":"SUV","spawnTime":734.6999999996218},{"specName":"VAN","spawnTime":756.0199999996024},{"specName":"SEDAN","spawnTime":772.2599999995876},{"specName":"SUV","spawnTime":780.8599999995798},{"specName":"SUV","spawnTime":788.399999999573},{"specName":"COUPE","spawnTime":791.69999999957},{"specName":"SUV","spawnTime":797.7399999995645},{"specName":"SUV","spawnTime":799.9199999995625},{"specName":"VAN","spawnTime":802.9399999995597},{"specName":"SUV","spawnTime":808.4799999995547},{"specName":"COUPE","spawnTime":810.4399999995529},{"specName":"SEDAN","spawnTime":813.1199999995505},{"specName":"SEDAN","spawnTime":825.1799999995395},{"specName":"VAN","spawnTime":828.5399999995365},{"specName":"SUV","spawnTime":833.399999999532},{"specName":"SUV","spawnTime":838.4399999995275},{"specName":"VAN","spawnTime":841.8399999995244},{"specName":"SEDAN","spawnTime":849.7999999995171},{"specName":"SUV","spawnTime":855.9199999995116},{"specName":"SUV","spawnTime":861.8599999995062},{"specName":"COUPE","spawnTime":868.6999999994999},{"specName":"VAN","spawnTime":875.279999999494},{"specName":"SEDAN","spawnTime":877.379999999492},{"specName":"COUPE","spawnTime":881.2399999994885},{"specName":"VAN","spawnTime":885.4999999994847},{"specName":"VAN","spawnTime":889.1799999994813},{"specName":"COUPE","spawnTime":892.5999999994782},{"specName":"VAN","spawnTime":894.8999999994761},{"specName":"VAN","spawnTime":900.6999999994708},{"specName":"SEDAN","spawnTime":904.4199999994674},{"specName":"COUPE","spawnTime":924.9799999994488},{"specName":"COUPE","spawnTime":928.2799999994457},{"specName":"COUPE","spawnTime":932.6399999994418},{"specName":"SUV","spawnTime":935.8199999994389},{"specName":"VAN","spawnTime":938.7399999994362},{"specName":"SUV","spawnTime":942.7599999994326},{"specName":"SEDAN","spawnTime":946.5199999994292},{"specName":"COUPE","spawnTime":950.5999999994254},{"specName":"COUPE","spawnTime":952.5599999994237},{"specName":"COUPE","spawnTime":956.0199999994205},{"specName":"VAN","spawnTime":962.4999999994146},{"specName":"SUV","spawnTime":964.7799999994126},{"specName":"COUPE","spawnTime":967.9399999994097},{"specName":"SUV","spawnTime":974.7199999994035},{"specName":"SUV","spawnTime":976.6599999994017},{"specName":"SUV","spawnTime":978.3799999994002},{"specName":"COUPE","spawnTime":980.1999999993985},{"specName":"VAN","spawnTime":983.0799999993959},{"specName":"VAN","spawnTime":984.9599999993942},{"specName":"COUPE","spawnTime":987.9799999993915},{"specName":"SEDAN","spawnTime":989.8399999993898},{"specName":"SUV","spawnTime":991.779999999388},{"specName":"COUPE","spawnTime":996.2799999993839},{"specName":"VAN","spawnTime":999.7399999993808}]
