[{"specName":"COUPE","spawnTime":0.6000000000000002},{"specName":"SEDAN","spawnTime":2.4200000000000017},{"specName":"COUPE","spawnTime":14.139999999999787},{"specName":"VAN","spawnTime":16.33999999999974},{"specName":"SEDAN","spawnTime":18.73999999999969},{"specName":"COUPE","spawnTime":28.259999999999486},{"specName":"SUV","spawnTime":31.139999999999425},{"specName":"SUV","spawnTime":36.86000000000016},{"specName":"SEDAN","spawnTime":40.06000000000066},{"specName":"VAN","spawnTime":41.78000000000093},{"specName":"SEDAN","spawnTime":47.06000000000176},{"specName":"SEDAN","spawnTime":53.40000000000275},{"specName":"SEDAN","spawnTime":55.44000000000307},{"specName":"COUPE","spawnTime":59.5000000000037},{"specName":"COUPE","spawnTime":62.90000000000423},{"specName":"VAN","spawnTime":65.22000000000416},{"specName":"VAN","spawnTime":68.0600000000036},{"specName":"SEDAN","spawnTime":70.42000000000313},{"specName":"COUPE","spawnTime":76.120000000002},{"specName":"SEDAN","spawnTime":83.26000000000057},{"specName":"SEDAN","spawnTime":86.81999999999987},{"specName":"COUPE","spawnTime":89.75999999999928},{"specName":"SUV","spawnTime":91.59999999999891},{"specName":"VAN","spawnTime":94.53999999999833},{"specName":"SEDAN","spawnTime":97.59999999999772},{"specName":"SUV","spawnTime":101.55999999999693},{"specName":"SUV","spawnTime":104.85999999999628},{"specName":"COUPE","spawnTime":109.7999999999953},{"specName":"SUV","spawnTime":112.7599999999947},{"specName":"SUV","spawnTime":115.47999999999416},{"specName":"COUPE","spawnTime":122.19999999999283},{"specName":"SEDAN","spawnTime":128.37999999999187},{"specName":"VAN","spawnTime":132.41999999999393},{"specName":"SUV","spawnTime":139.85999999999774},{"specName":"SEDAN","spawnTime":147.4200000000016},{"specName":"SEDAN","spawnTime":152.5000000000042},{"specName":"VAN","spawnTime":156.34000000000617},{"specName":"COUPE","spawnTime":161.4600000000088},{"specName":"SUV","spawnTime":166.44000000001134},{"specName":"COUPE","spawnTime":168.5000000000124},{"specName":"COUPE","spawnTime":182.86000000001974},{"specName":"SUV","spawnTime":193.42000000002514},{"specName":"SEDAN","spawnTime":202.7000000000299},{"specName":"COUPE","spawnTime":206.28000000003172},{"specName":"VAN","spawnTime":210.58000000003392},{"specName":"COUPE","spawnTime":212.78000000003505},{"specName":"SUV","spawnTime":214.8400000000361},{"specName":"COUPE","spawnTime":221.6600000000396},{"specName":"SEDAN","spawnTime":227.22000000004243},{"specName":"VAN","spawnTime":229.4800000000436},{"specName":"SEDAN","spawnTime":231.54000000004464},{"specName":"SUV","spawnTime":240.6400000000493},{"specName":"SEDAN","spawnTime":245.88000000005198},{"specName":"SUV","spawnTime":247.74000000005293},{"specName":"COUPE","spawnTime":256.6800000000565},{"specName":"SUV","spawnTime":272.34000000004227},{"specName":"VAN","spawnTime":274.82000000004},{"specName":"VAN","spawnTime":280.60000000003475},{"specName":"SUV","spawnTime":284.4000000000313},{"specName":"SEDAN","spawnTime":287.0400000000289},{"specName":"SUV","spawnTime":292.400000000024},{"specName":"VAN","spawnTime":295.8400000000209},{"specName":"COUPE","spawnTime":298.0600000000189},{"specName":"COUPE","spawnTime":300.16000000001696},{"specName":"SEDAN","spawnTime":303.02000000001436},{"specName":"SEDAN","spawnTime":304.7600000000128},{"specName":"COUPE","spawnTime":313.82000000000454},{"specName":"COUPE","spawnTime":317.0400000000016},{"specName":"SUV","spawnTime":319.6799999999992},{"specName":"COUPE","spawnTime":327.63999999999197},{"specName":"SEDAN","spawnTime":331.8799999999881},{"specName":"VAN","spawnTime":338.75999999998186},{"specName":"SEDAN","spawnTime":346.6199999999747},{"specName":"SEDAN","spawnTime":348.8399999999727},{"specName":"VAN","spawnTime":359.0799999999634},{"specName":"COUPE","spawnTime":370.85999999995266},{"specName":"VAN","spawnTime":373.2399999999505},{"specName":"SEDAN","spawnTime":388.1799999999369},{"specName":"SUV","spawnTime":399.7599999999264},{"specName":"COUPE","spawnTime":410.43999999991667},{"specName":"SUV","spawnTime":414.95999999991255},{"specName":"COUPE","spawnTime":419.59999999990833},{"specName":"SUV","spawnTime":433.89999999989533},{"specName":"SEDAN","spawnTime":441.43999999988847},{"specName":"SEDAN","spawnTime":443.33999999988674},{"specName":"SUV","spawnTime":446.4799999998839},{"specName":"SEDAN","spawnTime":458.419999999873},{"specName":"VAN","spawnTime":462.33999999986946},{"specName":"SEDAN","spawnTime":464.2599999998677},{"specName":"COUPE","spawnTime":468.6599999998637},{"specName":"SEDAN","spawnTime":474.45999999985844},{"specName":"SUV","spawnTime":480.5399999998529},{"specName":"SUV","spawnTime":490.0999999998442},{"specName":"COUPE","spawnTime":498.4999999998366},{"specName":"COUPE","spawnTime":500.4799999998348},{"specName":"SEDAN","spawnTime":503.6199999998319},{"specName":"SEDAN","spawnTime":507.3799999998285},{"specName":"SEDAN","spawnTime":511.5399999998247},{"specName":"VAN","spawnTime":514.2999999998223},{"specName":"COUPE","spawnTime":525.7999999998118},{"specName":"VAN","spawnTime":527.5399999998102},{"specName":"COUPE","spawnTime":531.5799999998065},{"specName":"SUV","spawnTime":537.3799999998013},{"specName":"SEDAN","spawnTime":540.1999999997987},{"specName":"VAN","spawnTime":546.7599999997927},{"specName":"SEDAN","spawnTime":555.239999999785},{"specName":"SEDAN","spawnTime":557.0599999997834},{"specName":"SEDAN","spawnTime":568.5599999997729},{"specName":"SUV","spawnTime":574.1799999997678},{"specName":"SEDAN","spawnTime":576.8999999997653},{"specName":"SUV","spawnTime":587.2999999997559},{"specName":"COUPE","spawnTime":589.7799999997536},{"specName":"SEDAN","spawnTime":592.639999999751},{"specName":"SUV","spawnTime":597.2199999997468},{"specName":"SUV","spawnTime":608.9799999997362},{"specName":"VAN","spawnTime":614.7199999997309},{"specName":"VAN","spawnTime":616.5399999997293},{"specName":"COUPE","spawnTime":619.1999999997269},{"specName":"VAN","spawnTime":626.3999999997203},{"specName":"COUPE","spawnTime":628.3399999997185},{"specName":"SUV","spawnTime":635.4199999997121},{"specName":"SEDAN","spawnTime":639.5999999997083},{"specName":"VAN","spawnTime":642.4399999997057},{"specName":"VAN","spawnTime":651.2999999996977},{"specName":"COUPE","spawnTime":654.1199999996951},{"specName":"VAN","spawnTime":667.479999999683},{"specName":"COUPE","spawnTime":671.4799999996793},{"specName":"COUPE","spawnTime":673.7999999996772},{"specName":"COUPE","spawnTime":678.8199999996726},{"specName":"VAN","spawnTime":683.0999999996687},{"specName":"COUPE","spawnTime":685.3199999996667},{"specName":"SUV","spawnTime":695.5399999996574},{"specName":"COUPE","spawnTime":699.7399999996536},{"specName":"SEDAN","spawnTime":702.0199999996515},{"specName":"VAN","spawnTime":706.0199999996479},{"specName":"COUPE","spawnTime":717.959999999637},{"specName":"SUV","spawnTime":720.199999999635},{"specName":"SEDAN","spawnTime":723.9199999996316},{"specName":"SUV","spawnTime":725.6199999996301},{"specName":"SUV","spawnTime":731.199999999625},{"specName":"SUV","spawnTime":738.7999999996181},{"specName":"COUPE","spawnTime":743.1599999996141},{"specName":"SEDAN","spawnTime":745.8799999996116},{"specName":"SUV","spawnTime":747.8399999996099},{"specName":"COUPE","spawnTime":752.8599999996053},{"specName":"COUPE","spawnTime":756.7599999996017},{"specName":"SUV","spawnTime":759.3799999995994},{"specName":"SUV","spawnTime":764.4399999995948},{"specName":"SEDAN","spawnTime":766.5799999995928},{"specName":"SEDAN","spawnTime":771.5999999995882},{"specName":"VAN","spawnTime":775.6799999995845},{"specName":"VAN","spawnTime":779.519999999581},{"specName":"SEDAN","spawnTime":782.7599999995781},{"specName":"VAN","spawnTime":787.4399999995738},{"specName":"SUV","spawnTime":806.0399999995569},{"specName":"COUPE","spawnTime":812.2999999995512},{"specName":"SUV","spawnTime":815.1199999995487},{"specName":"SUV","spawnTime":824.4199999995402},{"specName":"SEDAN","spawnTime":828.2599999995367},{"specName":"COUPE","spawnTime":831.3199999995339},{"specName":"SUV","spawnTime":838.1399999995277},{"specName":"SUV","spawnTime":843.8999999995225},{"specName":"SEDAN","spawnTime":846.7999999995199},{"specName":"SEDAN","spawnTime":850.6799999995163},{"specName":"VAN","spawnTime":852.9799999995142},{"specName":"SEDAN","spawnTime":855.0599999995123},{"specName":"VAN","spawnTime":857.4999999995101},{"specName":"SEDAN","spawnTime":861.5199999995065},{"specName":"VAN","spawnTime":864.3999999995038},{"specName":"COUPE","spawnTime":869.759999999499},{"specName":"VAN","spawnTime":874.179999999495},{"specName":"SUV","spawnTime":879.0799999994905},{"specName":"VAN","spawnTime":888.0199999994824},{"specName":"SEDAN","spawnTime":891.759999999479},{"specName":"COUPE","spawnTime":893.6799999994772},{"specName":"VAN","spawnTime":895.2999999994757},{"specName":"SUV","spawnTime":901.0399999994705},{"specName":"VAN","spawnTime":905.3999999994666},{"specName":"VAN","spawnTime":909.6199999994627},{"specName":"COUPE","spawnTime":912.57999999946},{"specName":"SEDAN","spawnTime":924.9999999994487},{"specName":"COUPE","spawnTime":927.4799999994465},{"specName":"COUPE","spawnTime":943.1999999994322},{"specName":"COUPE","spawnTime":944.8799999994307},{"specName":"COUPE","spawnTime":948.5799999994273},{"specName":"VAN","spawnTime":954.8799999994216},{"specName":"VAN","spawnTime":959.5599999994173},{"specName":"COUPE","spawnTime":966.0799999994114},{"specName":"VAN","spawnTime":971.2799999994066},{"specName":"VAN","spawnTime":983.6799999993954},{"specName":"SUV","spawnTime":986.239999999393},{"specName":"VAN","spawnTime":989.1999999993903},{"specName":"VAN","spawnTime":997.9799999993824}]
