[{"specName":"SEDAN","spawnTime":0.25999999999999995},{"specName":"COUPE","spawnTime":9.439999999999888},{"specName":"VAN","spawnTime":11.419999999999845},{"specName":"VAN","spawnTime":12.999999999999812},{"specName":"SUV","spawnTime":14.259999999999785},{"specName":"SEDAN","spawnTime":17.37999999999972},{"specName":"VAN","spawnTime":22.199999999999616},{"specName":"SUV","spawnTime":23.159999999999595},{"specName":"SEDAN","spawnTime":26.519999999999524},{"specName":"COUPE","spawnTime":36.4600000000001},{"specName":"COUPE","spawnTime":39.08000000000051},{"specName":"VAN","spawnTime":41.06000000000082},{"specName":"SEDAN","spawnTime":44.32000000000133},{"specName":"SUV","spawnTime":45.760000000001554},{"specName":"COUPE","spawnTime":46.74000000000171},{"specName":"COUPE","spawnTime":49.2600000000021},{"specName":"SEDAN","spawnTime":52.480000000002605},{"specName":"VAN","spawnTime":65.74000000000406},{"specName":"SUV","spawnTime":73.00000000000261},{"specName":"VAN","spawnTime":75.5800000000021},{"specName":"VAN","spawnTime":76.6200000000019},{"specName":"COUPE","spawnTime":80.86000000000105},{"specName":"VAN","spawnTime":88.41999999999955},{"specName":"COUPE","spawnTime":90.95999999999904},{"specName":"COUPE","spawnTime":95.07999999999822},{"specName":"COUPE","spawnTime":101.41999999999696},{"specName":"SEDAN","spawnTime":108.05999999999564},{"specName":"COUPE","spawnTime":114.59999999999434},{"specName":"SUV","spawnTime":116.35999999999399},{"specName":"SUV","spawnTime":118.95999999999347},{"specName":"SEDAN","spawnTime":124.73999999999232},{"specName":"COUPE","spawnTime":127.3599999999918},{"specName":"SUV","spawnTime":128.4199999999919},{"specName":"SEDAN","spawnTime":129.29999999999234},{"specName":"SUV","spawnTime":133.99999999999474},{"specName":"SEDAN","spawnTime":145.0800000000004},{"specName":"SEDAN","spawnTime":146.8000000000013},{"specName":"VAN","spawnTime":148.5800000000022},{"specName":"SEDAN","spawnTime":153.2600000000046},{"specName":"SEDAN","spawnTime":154.80000000000538},{"specName":"VAN","spawnTime":159.7200000000079},{"specName":"COUPE","spawnTime":160.76000000000843},{"specName":"SUV","spawnTime":162.18000000000916},{"specName":"SUV","spawnTime":163.0400000000096},{"specName":"COUPE","spawnTime":171.80000000001408},{"specName":"SEDAN","spawnTime":180.74000000001865},{"specName":"COUPE","spawnTime":183.5600000000201},{"specName":"COUPE","spawnTime":193.66000000002526},{"specName":"SEDAN","spawnTime":200.02000000002852},{"specName":"SUV","spawnTime":201.1400000000291},{"specName":"COUPE","spawnTime":204.24000000003068},{"specName":"VAN","spawnTime":215.4400000000364},{"specName":"COUPE","spawnTime":216.52000000003696},{"specName":"SUV","spawnTime":222.2800000000399},{"specName":"COUPE","spawnTime":224.88000000004124},{"specName":"COUPE","spawnTime":227.1800000000424},{"specName":"VAN","spawnTime":229.5200000000436},{"specName":"SUV","spawnTime":231.16000000004445},{"specName":"VAN","spawnTime":236.30000000004708},{"specName":"SEDAN","spawnTime":239.32000000004862},{"specName":"SEDAN","spawnTime":241.08000000004952},{"specName":"VAN","spawnTime":242.48000000005024},{"specName":"VAN","spawnTime":245.88000000005198},{"specName":"SUV","spawnTime":247.72000000005292},{"specName":"COUPE","spawnTime":249.40000000005378},{"specName":"SEDAN","spawnTime":251.6000000000549},{"specName":"SEDAN","spawnTime":255.40000000005685},{"specName":"SUV","spawnTime":256.30000000005685},{"specName":"COUPE","spawnTime":259.16000000005425},{"specName":"VAN","spawnTime":260.560000000053},{"specName":"SEDAN","spawnTime":263.3800000000504},{"specName":"COUPE","spawnTime":267.2400000000469},{"specName":"SEDAN","spawnTime":269.2000000000451},{"specName":"SUV","spawnTime":270.82000000004365},{"specName":"VAN","spawnTime":273.720000000041},{"specName":"VAN","spawnTime":276.52000000003846},{"specName":"COUPE","spawnTime":286.5000000000294},{"specName":"SUV","spawnTime":291.0200000000253},{"specName":"COUPE","spawnTime":297.08000000001977},{"specName":"COUPE","spawnTime":301.50000000001575},{"specName":"SUV","spawnTime":309.50000000000847},{"specName":"SEDAN","spawnTime":313.8600000000045},{"specName":"SUV","spawnTime":315.36000000000314},{"specName":"SEDAN","spawnTime":319.0399999999998},{"specName":"COUPE","spawnTime":321.49999999999756},{"specName":"SUV","spawnTime":328.6199999999911},{"specName":"COUPE","spawnTime":331.7599999999882},{"specName":"SEDAN","spawnTime":333.27999999998684},{"specName":"COUPE","spawnTime":334.4399999999858},{"specName":"SEDAN","spawnTime":335.5399999999848},{"specName":"COUPE","spawnTime":336.399999999984},{"specName":"COUPE","spawnTime":340.65999999998013},{"specName":"VAN","spawnTime":341.85999999997904},{"specName":"SUV","spawnTime":346.91999999997444},{"specName":"SUV","spawnTime":358.8599999999636},{"specName":"VAN","spawnTime":360.1799999999624},{"specName":"SEDAN","spawnTime":364.51999999995843},{"specName":"SEDAN","spawnTime":371.6799999999519},{"specName":"COUPE","spawnTime":375.8599999999481},{"specName":"VAN","spawnTime":377.35999999994675},{"specName":"SUV","spawnTime":381.1799999999433},{"specName":"SUV","spawnTime":387.9799999999371},{"specName":"SUV","spawnTime":394.3399999999313},{"specName":"COUPE","spawnTime":399.8399999999263},{"specName":"SEDAN","spawnTime":404.0399999999225},{"specName":"COUPE","spawnTime":406.91999999991987},{"specName":"VAN","spawnTime":408.959999999918},{"specName":"COUPE","spawnTime":414.2799999999132},{"specName":"SEDAN","spawnTime":416.81999999991086},{"specName":"SEDAN","spawnTime":417.77999999991},{"specName":"VAN","spawnTime":418.69999999990915},{"specName":"SEDAN","spawnTime":420.9599999999071},{"specName":"SUV","spawnTime":425.19999999990324},{"specName":"SEDAN","spawnTime":430.8599999998981},{"specName":"SEDAN","spawnTime":433.5199999998957},{"specName":"SEDAN","spawnTime":437.1399999998924},{"specName":"COUPE","spawnTime":438.7599999998909},{"specName":"COUPE","spawnTime":441.11999999988876},{"specName":"COUPE","spawnTime":447.81999999988267},{"specName":"SEDAN","spawnTime":448.69999999988187},{"specName":"SEDAN","spawnTime":453.8399999998772},{"specName":"COUPE","spawnTime":472.99999999985977},{"specName":"SUV","spawnTime":478.39999999985486},{"specName":"SEDAN","spawnTime":481.6599999998519},{"specName":"COUPE","spawnTime":490.359999999844},{"specName":"SUV","spawnTime":492.4199999998421},{"specName":"SEDAN","spawnTime":493.81999999984083},{"specName":"SEDAN","spawnTime":507.51999999982837},{"specName":"SUV","spawnTime":510.4399999998257},{"specName":"SEDAN","spawnTime":513.3799999998231},{"specName":"COUPE","spawnTime":514.9799999998216},{"specName":"COUPE","spawnTime":517.4399999998194},{"specName":"SEDAN","spawnTime":519.2199999998178},{"specName":"VAN","spawnTime":521.7999999998154},{"specName":"VAN","spawnTime":526.1999999998114},{"specName":"COUPE","spawnTime":538.8399999997999},{"specName":"SUV","spawnTime":541.2999999997977},{"specName":"VAN","spawnTime":560.6999999997801},{"specName":"SUV","spawnTime":561.6599999997792},{"specName":"COUPE","spawnTime":564.4199999997767},{"specName":"SUV","spawnTime":566.3599999997749},{"specName":"SEDAN","spawnTime":573.0999999997688},{"specName":"VAN","spawnTime":582.3199999997604},{"specName":"COUPE","spawnTime":583.899999999759},{"specName":"SEDAN","spawnTime":587.119999999756},{"specName":"VAN","spawnTime":588.5599999997547},{"specName":"SEDAN","spawnTime":591.8999999997517},{"specName":"SUV","spawnTime":593.3199999997504},{"specName":"SUV","spawnTime":595.4799999997484},{"specName":"SEDAN","spawnTime":598.199999999746},{"specName":"SEDAN","spawnTime":602.579999999742},{"specName":"SUV","spawnTime":608.9799999997362},{"specName":"VAN","spawnTime":617.2799999997286},{"specName":"SEDAN","spawnTime":620.6799999997255},{"specName":"SUV","spawnTime":622.0799999997242},{"specName":"SUV","spawnTime":622.9399999997235},{"specName":"VAN","spawnTime":627.2799999997195},{"specName":"SEDAN","spawnTime":631.2799999997159},{"specName":"COUPE","spawnTime":634.0999999997133},{"specName":"SEDAN","spawnTime":636.8999999997108},{"specName":"SEDAN","spawnTime":638.7599999997091},{"specName":"VAN","spawnTime":645.2399999997032},{"specName":"SEDAN","spawnTime":646.2199999997023},{"specName":"SUV","spawnTime":647.0799999997015},{"specName":"VAN","spawnTime":652.2599999996968},{"specName":"SUV","spawnTime":656.9799999996925},{"specName":"SEDAN","spawnTime":665.8599999996844},{"specName":"COUPE","spawnTime":667.9199999996825},{"specName":"SUV","spawnTime":674.9799999996761},{"specName":"SUV","spawnTime":676.9799999996743},{"specName":"COUPE","spawnTime":679.7799999996718},{"specName":"SUV","spawnTime":690.9999999996616},{"specName":"VAN","spawnTime":694.1799999996587},{"specName":"SEDAN","spawnTime":697.7399999996554},{"specName":"VAN","spawnTime":700.1399999996532},{"specName":"SEDAN","spawnTime":705.5999999996483},{"specName":"COUPE","spawnTime":707.1599999996469},{"specName":"SUV","spawnTime":718.8199999996363},{"specName":"SUV","spawnTime":719.9799999996352},{"specName":"SUV","spawnTime":728.3799999996276},{"specName":"SUV","spawnTime":732.7799999996236},{"specName":"COUPE","spawnTime":738.6999999996182},{"specName":"VAN","spawnTime":743.3999999996139},{"specName":"VAN","spawnTime":744.9399999996125},{"specName":"SEDAN","spawnTime":746.7799999996108},{"specName":"COUPE","spawnTime":752.5199999996056},{"specName":"SEDAN","spawnTime":766.1599999995932},{"specName":"COUPE","spawnTime":772.6399999995873},{"specName":"VAN","spawnTime":776.7399999995836},{"specName":"SUV","spawnTime":780.1999999995804},{"specName":"COUPE","spawnTime":784.1599999995768},{"specName":"SUV","spawnTime":791.9599999995697},{"specName":"COUPE","spawnTime":796.1399999995659},{"specName":"VAN","spawnTime":799.6199999995628},{"specName":"SEDAN","spawnTime":800.7999999995617},{"specName":"VAN","spawnTime":801.7799999995608},{"specName":"SUV","spawnTime":808.7799999995544},{"specName":"COUPE","spawnTime":810.319999999553},{"specName":"SEDAN","spawnTime":827.2999999995376},{"specName":"VAN","spawnTime":829.7399999995354},{"specName":"COUPE","spawnTime":835.8399999995298},{"specName":"SEDAN","spawnTime":838.7599999995272},{"specName":"COUPE","spawnTime":841.3999999995248},{"specName":"SUV","spawnTime":850.8999999995161},{"specName":"SEDAN","spawnTime":852.7799999995144},{"specName":"VAN","spawnTime":853.9599999995133},{"specName":"VAN","spawnTime":858.4399999995093},{"specName":"VAN","spawnTime":860.7199999995072},{"specName":"VAN","spawnTime":867.6399999995009},{"specName":"VAN","spawnTime":869.8999999994988},{"specName":"SUV","spawnTime":870.9199999994979},{"specName":"COUPE","spawnTime":874.0199999994951},{"specName":"VAN","spawnTime":876.4199999994929},{"specName":"SUV","spawnTime":881.6199999994882},{"specName":"SUV","spawnTime":901.3999999994702},{"specName":"COUPE","spawnTime":916.2399999994567},{"specName":"COUPE","spawnTime":917.9199999994552},{"specName":"VAN","spawnTime":919.6799999994536},{"specName":"SEDAN","spawnTime":929.3399999994448},{"specName":"COUPE","spawnTime":930.5999999994436},{"specName":"SUV","spawnTime":931.8799999994425},{"specName":"COUPE","spawnTime":937.5199999994373},{"specName":"SUV","spawnTime":940.3799999994347},{"specName":"COUPE","spawnTime":946.9399999994288},{"specName":"VAN","spawnTime":950.5799999994255},{"specName":"SUV","spawnTime":953.1999999994231},{"specName":"SUV","spawnTime":954.6799999994217},{"specName":"COUPE","spawnTime":964.0399999994132},{"specName":"SEDAN","spawnTime":967.3399999994102},{"specName":"SEDAN","spawnTime":971.3799999994066},{"specName":"SUV","spawnTime":978.0199999994005},{"specName":"SUV","spawnTime":979.1799999993995},{"specName":"SUV","spawnTime":984.099999999395},{"specName":"VAN","spawnTime":986.5999999993927},{"specName":"COUPE","spawnTime":998.4599999993819}]
